LICENSE-MIT
setup.py
braindump/__init__.py
braindump/__main__.py
braindump/cmdline.py
braindump/core.py
braindump.egg-info/PKG-INFO
braindump.egg-info/SOURCES.txt
braindump.egg-info/dependency_links.txt
braindump.egg-info/entry_points.txt
braindump.egg-info/requires.txt
braindump.egg-info/top_level.txt
braindump/dumpers/FSDumper.py
braindump/dumpers/__init__.py