Metadata-Version: 1.0
Name: braindump
Version: 0.0.8
Summary: 
